{
  "module_name": "auto_addr_example",
  "data_width": 32,
  "addr_width": 8,
  "num_write_ports": 1,
  "num_read_ports": 1,
  "sync_reset": false,
  "reset_value": "0x00000000",
  "byte_enable": true,
  "auto_address": true,
  "registers": [
    {
      "name": "CTRL_REG",
      "type": "ReadWrite",
      "reset_value": "0x00000000",
      "description": "控制寄存器"
    },
    {
      "name": "STATUS_REG",
      "type": "ReadOnly",
      "reset_value": "0x00000000",
      "description": "状态寄存器"
    },
    {
      "name": "INTR_REG",
      "type": "Write1Clean",
      "reset_value": "0x00000000",
      "description": "中断寄存器"
    },
    {
      "name": "CONFIG1_REG",
      "type": "ReadWrite",
      "reset_value": "0x00000000",
      "description": "配置寄存器1"
    },
    {
      "name": "CONFIG2_REG",
      "type": "ReadWrite",
      "reset_value": "0x00000000",
      "description": "配置寄存器2"
    },
    {
      "name": "VERSION_REG",
      "type": "ReadOnly",
      "reset_value": "0x00010000",
      "description": "版本寄存器"
    }
  ],
  "fields": [
    {
      "register": "CTRL_REG",
      "name": "ENABLE",
      "bit_range": "0",
      "description": "使能位"
    },
    {
      "register": "CTRL_REG",
      "name": "MODE",
      "bit_range": "2:1",
      "description": "模式设置"
    },
    {
      "register": "STATUS_REG",
      "name": "BUSY",
      "bit_range": "0",
      "description": "忙标志"
    },
    {
      "register": "STATUS_REG",
      "name": "ERROR",
      "bit_range": "1",
      "description": "错误标志"
    },
    {
      "register": "INTR_REG",
      "name": "DONE",
      "bit_range": "0",
      "description": "完成中断"
    },
    {
      "register": "INTR_REG",
      "name": "ERROR",
      "bit_range": "1",
      "description": "错误中断"
    },
    {
      "register": "CONFIG1_REG",
      "name": "TIMEOUT",
      "bit_range": "7:0",
      "description": "超时设置"
    },
    {
      "register": "CONFIG2_REG",
      "name": "CLK_DIV",
      "bit_range": "7:0",
      "description": "时钟分频设置"
    },
    {
      "register": "VERSION_REG",
      "name": "MAJOR",
      "bit_range": "15:8",
      "description": "主版本号"
    },
    {
      "register": "VERSION_REG",
      "name": "MINOR",
      "bit_range": "7:0",
      "description": "次版本号"
    }
  ]
} 